{
  "source": "https://www.sec.gov/files/company_tickers.json",
  "generated_at": "2026-05-26T22:48:00+09:00",
  "symbols": {
    "AAPL": {
      "cik": "0000320193",
      "ticker": "AAPL",
      "title": "Apple Inc."
    },
    "ABBV": {
      "cik": "0001551152",
      "ticker": "ABBV",
      "title": "AbbVie Inc."
    },
    "ADBE": {
      "cik": "0000796343",
      "ticker": "ADBE",
      "title": "ADOBE INC."
    },
    "AMAT": {
      "cik": "0000006951",
      "ticker": "AMAT",
      "title": "APPLIED MATERIALS INC /DE"
    },
    "AMD": {
      "cik": "0000002488",
      "ticker": "AMD",
      "title": "ADVANCED MICRO DEVICES INC"
    },
    "AMZN": {
      "cik": "0001018724",
      "ticker": "AMZN",
      "title": "AMAZON COM INC"
    },
    "ASML": {
      "cik": "0000937966",
      "ticker": "ASML",
      "title": "ASML HOLDING NV"
    },
    "AVGO": {
      "cik": "0001730168",
      "ticker": "AVGO",
      "title": "Broadcom Inc."
    },
    "BA": {
      "cik": "0000012927",
      "ticker": "BA",
      "title": "BOEING CO"
    },
    "BAC": {
      "cik": "0000070858",
      "ticker": "BAC",
      "title": "BANK OF AMERICA CORP /DE/"
    },
    "CAT": {
      "cik": "0000018230",
      "ticker": "CAT",
      "title": "CATERPILLAR INC"
    },
    "COIN": {
      "cik": "0001679788",
      "ticker": "COIN",
      "title": "Coinbase Global, Inc."
    },
    "COP": {
      "cik": "0001163165",
      "ticker": "COP",
      "title": "CONOCOPHILLIPS"
    },
    "COST": {
      "cik": "0000909832",
      "ticker": "COST",
      "title": "COSTCO WHOLESALE CORP /NEW"
    },
    "CRM": {
      "cik": "0001108524",
      "ticker": "CRM",
      "title": "Salesforce, Inc."
    },
    "CVX": {
      "cik": "0000093410",
      "ticker": "CVX",
      "title": "CHEVRON CORP"
    },
    "ETN": {
      "cik": "0001551182",
      "ticker": "ETN",
      "title": "Eaton Corp plc"
    },
    "FCX": {
      "cik": "0000831259",
      "ticker": "FCX",
      "title": "FREEPORT-MCMORAN INC"
    },
    "GE": {
      "cik": "0000040545",
      "ticker": "GE",
      "title": "GENERAL ELECTRIC CO"
    },
    "GOOGL": {
      "cik": "0001652044",
      "ticker": "GOOGL",
      "title": "Alphabet Inc."
    },
    "GS": {
      "cik": "0000886982",
      "ticker": "GS",
      "title": "GOLDMAN SACHS GROUP INC"
    },
    "HD": {
      "cik": "0000354950",
      "ticker": "HD",
      "title": "HOME DEPOT, INC."
    },
    "HON": {
      "cik": "0000773840",
      "ticker": "HON",
      "title": "HONEYWELL INTERNATIONAL INC"
    },
    "HOOD": {
      "cik": "0001783879",
      "ticker": "HOOD",
      "title": "Robinhood Markets, Inc."
    },
    "INTC": {
      "cik": "0000050863",
      "ticker": "INTC",
      "title": "INTEL CORP"
    },
    "IONQ": {
      "cik": "0001824920",
      "ticker": "IONQ",
      "title": "IonQ, Inc."
    },
    "ISRG": {
      "cik": "0001035267",
      "ticker": "ISRG",
      "title": "INTUITIVE SURGICAL INC"
    },
    "JNJ": {
      "cik": "0000200406",
      "ticker": "JNJ",
      "title": "JOHNSON & JOHNSON"
    },
    "JPM": {
      "cik": "0000019617",
      "ticker": "JPM",
      "title": "JPMORGAN CHASE & CO"
    },
    "KLAC": {
      "cik": "0000319201",
      "ticker": "KLAC",
      "title": "KLA CORP"
    },
    "LIN": {
      "cik": "0001707925",
      "ticker": "LIN",
      "title": "LINDE PLC"
    },
    "LLY": {
      "cik": "0000059478",
      "ticker": "LLY",
      "title": "ELI LILLY & Co"
    },
    "LRCX": {
      "cik": "0000707549",
      "ticker": "LRCX",
      "title": "LAM RESEARCH CORP"
    },
    "MA": {
      "cik": "0001141391",
      "ticker": "MA",
      "title": "Mastercard Inc"
    },
    "MCD": {
      "cik": "0000063908",
      "ticker": "MCD",
      "title": "MCDONALDS CORP"
    },
    "META": {
      "cik": "0001326801",
      "ticker": "META",
      "title": "Meta Platforms, Inc."
    },
    "MRK": {
      "cik": "0000310158",
      "ticker": "MRK",
      "title": "Merck & Co., Inc."
    },
    "MS": {
      "cik": "0000895421",
      "ticker": "MS",
      "title": "MORGAN STANLEY"
    },
    "MSFT": {
      "cik": "0000789019",
      "ticker": "MSFT",
      "title": "MICROSOFT CORP"
    },
    "MU": {
      "cik": "0000723125",
      "ticker": "MU",
      "title": "MICRON TECHNOLOGY INC"
    },
    "NEE": {
      "cik": "0000753308",
      "ticker": "NEE",
      "title": "NEXTERA ENERGY INC"
    },
    "NKE": {
      "cik": "0000320187",
      "ticker": "NKE",
      "title": "NIKE, Inc."
    },
    "NOK": {
      "cik": "0000924613",
      "ticker": "NOK",
      "title": "NOKIA CORP"
    },
    "NVDA": {
      "cik": "0001045810",
      "ticker": "NVDA",
      "title": "NVIDIA CORP"
    },
    "ORCL": {
      "cik": "0001341439",
      "ticker": "ORCL",
      "title": "ORACLE CORP"
    },
    "PFE": {
      "cik": "0000078003",
      "ticker": "PFE",
      "title": "PFIZER INC"
    },
    "PLTR": {
      "cik": "0001321655",
      "ticker": "PLTR",
      "title": "Palantir Technologies Inc."
    },
    "QBTS": {
      "cik": "0001907982",
      "ticker": "QBTS",
      "title": "D-Wave Quantum Inc."
    },
    "QQQ": {
      "cik": "0001067839",
      "ticker": "QQQ",
      "title": "INVESCO QQQ TRUST, SERIES 1"
    },
    "RGTI": {
      "cik": "0001838359",
      "ticker": "RGTI",
      "title": "Rigetti Computing, Inc."
    },
    "RTX": {
      "cik": "0000101829",
      "ticker": "RTX",
      "title": "RTX Corp"
    },
    "SBUX": {
      "cik": "0000829224",
      "ticker": "SBUX",
      "title": "STARBUCKS CORP"
    },
    "SLB": {
      "cik": "0000087347",
      "ticker": "SLB",
      "title": "SLB LIMITED/NV"
    },
    "SO": {
      "cik": "0000092122",
      "ticker": "SO",
      "title": "SOUTHERN CO"
    },
    "SPY": {
      "cik": "0000884394",
      "ticker": "SPY",
      "title": "SPDR S&P 500 ETF TRUST"
    },
    "TSLA": {
      "cik": "0001318605",
      "ticker": "TSLA",
      "title": "Tesla, Inc."
    },
    "TSM": {
      "cik": "0001046179",
      "ticker": "TSM",
      "title": "TAIWAN SEMICONDUCTOR MANUFACTURING CO LTD"
    },
    "UNH": {
      "cik": "0000731766",
      "ticker": "UNH",
      "title": "UNITEDHEALTH GROUP INC"
    },
    "V": {
      "cik": "0001403161",
      "ticker": "V",
      "title": "VISA INC."
    },
    "WMT": {
      "cik": "0000104169",
      "ticker": "WMT",
      "title": "Walmart Inc."
    },
    "XOM": {
      "cik": "0000034088",
      "ticker": "XOM",
      "title": "EXXON MOBIL CORP"
    }
  },
  "missing_symbols": [
    "SMH"
  ]
}
